hid_parser/__init__.py
hid_parser/data.py
hidapi/__init__.py
hidapi/common.py
hidapi/hidapi_impl.py
hidapi/hidconsole.py
hidapi/udev_impl.py
keysyms/__init__.py
keysyms/generate.py
keysyms/keysymdef.py
logitech_receiver/__init__.py
logitech_receiver/base.py
logitech_receiver/base_usb.py
logitech_receiver/common.py
logitech_receiver/descriptors.py
logitech_receiver/desktop_notifications.py
logitech_receiver/device.py
logitech_receiver/diversion.py
logitech_receiver/exceptions.py
logitech_receiver/hidpp10.py
logitech_receiver/hidpp10_constants.py
logitech_receiver/hidpp20.py
logitech_receiver/hidpp20_constants.py
logitech_receiver/i18n.py
logitech_receiver/listener.py
logitech_receiver/notifications.py
logitech_receiver/receiver.py
logitech_receiver/settings.py
logitech_receiver/settings_new.py
logitech_receiver/settings_templates.py
logitech_receiver/settings_validator.py
logitech_receiver/special_keys.py
solaar/__init__.py
solaar/commit
solaar/configuration.py
solaar/custom_logger.py
solaar/dbus.py
solaar/gtk.py
solaar/i18n.py
solaar/listener.py
solaar/tasks.py
solaar/version
solaar/cli/__init__.py
solaar/cli/config.py
solaar/cli/pair.py
solaar/cli/probe.py
solaar/cli/profiles.py
solaar/cli/show.py
solaar/cli/unpair.py
solaar/ui/__init__.py
solaar/ui/action.py
solaar/ui/common.py
solaar/ui/config_panel.py
solaar/ui/desktop_notifications.py
solaar/ui/diversion_rules.py
solaar/ui/icons.py
solaar/ui/pair_window.py
solaar/ui/rule_actions.py
solaar/ui/rule_base.py
solaar/ui/rule_conditions.py
solaar/ui/tray.py
solaar/ui/window.py
solaar/ui/about/__init__.py
solaar/ui/about/about.py
solaar/ui/about/model.py
solaar/ui/about/presenter.py
solaar/ui/about/view.py
solaar-1.1.19.data/data/lib/udev/rules.d/42-logitech-unify-permissions.rules
solaar-1.1.19.data/data/share/applications/solaar.desktop
solaar-1.1.19.data/data/share/icons/hicolor/32x32/apps/solaar-light_000.png
solaar-1.1.19.data/data/share/icons/hicolor/32x32/apps/solaar-light_020.png
solaar-1.1.19.dist-info/licenses/LICENSE.txt
solaar-1.1.19.dist-info/METADATA
solaar-1.1.19.dist-info/WHEEL
solaar-1.1.19.dist-info/top_level.txt
solaar-1.1.19.dist-info/RECORD
